http_types/__init__.py
http_types/types.py
http_types/utils.py
http_types-0.0.18.dist-info/LICENSE
http_types-0.0.18.dist-info/METADATA
http_types-0.0.18.dist-info/WHEEL
http_types-0.0.18.dist-info/top_level.txt
http_types-0.0.18.dist-info/RECORD
