Metadata-Version: 2.1
Name: http-types
Version: 0.0.18
Summary: Types for HTTP requests and responses
Home-page: http://github.com/Meeshkan/py-http-types
Author: Meeshkan Dev Team
Author-email: dev@meeshkan.com
License: MIT
Platform: UNKNOWN
Classifier: Programming Language :: Python :: 3
Classifier: License :: OSI Approved :: MIT License
Classifier: Operating System :: OS Independent
Requires-Python: >=3.6.0
Requires-Dist: python-dateutil (>=2.8.1)
Requires-Dist: typeguard (>=2.7.0)
Requires-Dist: dataclasses ; python_version < "3.7"
Provides-Extra: dev
Requires-Dist: autopep8 ; extra == 'dev'
Requires-Dist: black ; extra == 'dev'
Requires-Dist: flake8 ; extra == 'dev'
Requires-Dist: jsonschema ; extra == 'dev'
Requires-Dist: mypy ; extra == 'dev'
Requires-Dist: pyhamcrest ; extra == 'dev'
Requires-Dist: pylint ; extra == 'dev'
Requires-Dist: pytest ; extra == 'dev'
Requires-Dist: pytest-testmon ; extra == 'dev'
Requires-Dist: pytest-watch ; extra == 'dev'
Requires-Dist: httpretty ; extra == 'dev'
Requires-Dist: setuptools ; extra == 'dev'
Requires-Dist: twine ; extra == 'dev'
Requires-Dist: wheel ; extra == 'dev'
